LICENSE
MANIFEST.in
README.md
setup.py
tap_ga360/__init__.py
tap_ga360/config.py
tap_ga360/schema.py
tap_ga360/streams.py
tap_ga360.egg-info/PKG-INFO
tap_ga360.egg-info/SOURCES.txt
tap_ga360.egg-info/dependency_links.txt
tap_ga360.egg-info/entry_points.txt
tap_ga360.egg-info/requires.txt
tap_ga360.egg-info/top_level.txt
tap_ga360/schemas/ga_session_hits.json
tap_ga360/schemas/ga_sessions.json