Metadata-Version: 2.1
Name: tap-ga360
Version: 0.2.2
Summary: Singer.io tap for extracting data from Google Analytics 360 via BigQuery
Home-page: https://singer.io
Author: Stitch
License: UNKNOWN
Platform: UNKNOWN
Classifier: Programming Language :: Python :: 3 :: Only
Provides-Extra: dev
License-File: LICENSE
